OSRSBytes/Hiscores.py
OSRSBytes/Items.py
OSRSBytes/Utilities.py
OSRSBytes/__init__.py
OSRSBytes/modules/fletching.json
OSRSBytes/modules/smithing.json
OSRSBytes/tests/__init__.py
OSRSBytes/tests/hiscores_test.py
OSRSBytes/tests/items_test.py
OSRSBytes-1.3.21.dist-info/LICENSE
OSRSBytes-1.3.21.dist-info/METADATA
OSRSBytes-1.3.21.dist-info/WHEEL
OSRSBytes-1.3.21.dist-info/top_level.txt
OSRSBytes-1.3.21.dist-info/RECORD
